{
  "lessons": [
    {
      "lesson_number": 1,
      "lesson_title": "Personal Pronouns and Basic Verb Conjugation",
      "lesson_sections": 4,
      "preliminary_notes": "\"Zqapa\" vowel = ā\n\"Pthaha\" = a\n\nExample: āna (Translation: I)\nExample: bāba (Translation: father)",
      "lesson_contents": [
        {
          "pronouns": {
            "singular": [
              {
                "pronoun": "āna",
                "translation": "I"
              },
              {
                "pronoun": "āyit",
                "translation": "You (masc.)"
              },
              {
                "pronoun": "āyat",
                "translation": "You (fem.)"
              },
              {
                "pronoun": "āwo",
                "translation": "He"
              },
              {
                "pronoun": "āya",
                "translation": "She"
              }
            ],
            "plural": [
              {
                "pronoun": "akhny",
                "translation": "We"
              },
              {
                "pronoun": "akhto",
                "translation": "You (plural)"
              },
              {
                "pronoun": "anay",
                "translation": "They"
              }
            ]
          },
          "verbs": [
            {
              "verb": "TO BE",
              "verb_root": "hwa",
              "verb_tense": "PRESENT",
              "conjugations": [
                {
                  "pronoun": "āna",
                  "conjugation": "ee-win",
                  "translation": "I (masc.) am"
                },
                {
                  "pronoun": "āyit",
                  "conjugation": "ee-wit",
                  "translation": "You (m) are"
                },
                {
                  "pronoun": "āna",
                  "conjugation": "ee-wan",
                  "translation": "I (fem) am"
                },
                {
                  "pronoun": "āyit",
                  "conjugation": "ee-wat",
                  "translation": "You (f) are"
                },
                {
                  "pronoun": "āwo",
                  "conjugation": "ee-lih",
                  "translation": "He is"
                },
                {
                  "pronoun": "āya",
                  "conjugation": "ee-lah",
                  "translation": "She is"
                },
                {
                  "pronoun": "akhny",
                  "conjugation": "ee-wookh",
                  "translation": "We are"
                },
                {
                  "pronoun": "akhto(n)",
                  "conjugation": "ee-wotoon",
                  "translation": "Y'all are"
                },
                {
                  "pronoun": "anay",
                  "conjugation": "ee-lay",
                  "translation": "They are"
                }
              ]
            },
            {
              "verb": "TO BE",
              "verb_root": "hwa",
              "verb_tense": "PAST",
              "conjugations": [
                {
                  "pronoun": "āna",
                  "conjugation": "win-wa",
                  "translation": "I (masc.) was"
                },
                {
                  "pronoun": "āyit",
                  "conjugation": "wit-wa",
                  "translation": "You (m) were"
                },
                {
                  "pronoun": "āna",
                  "conjugation": "wan-wa",
                  "translation": "I (fem) was"
                },
                {
                  "pronoun": "āyat",
                  "conjugation": "wet-wa",
                  "translation": "You (f) were"
                },
                {
                  "pronoun": "āwo",
                  "conjugation": "wae-wa",
                  "translation": "He was"
                },
                {
                  "pronoun": "āya",
                  "conjugation": "wa-wa",
                  "translation": "She was"
                },
                {
                  "pronoun": "akhny",
                  "conjugation": "wookh-wa",
                  "translation": "We were"
                },
                {
                  "pronoun": "akhto(n)",
                  "conjugation": "wot-wa or wotoon-wa",
                  "translation": "Y'all were"
                },
                {
                  "pronoun": "anay or anee",
                  "conjugation": "wa-wae",
                  "translation": "They were"
                }
              ]
            }
          ],
          "vocabulary": [
            {
              "word": "Talmeedha",
              "translation": "Student",
              "notes": "The dh is pronounced with the same noise as the 'th' in the word 'the'"
            },
            {
              "word": "Malpāna",
              "translation": "Teacher",
              "notes": null
            },
            {
              "word": "Madrasa",
              "translation": "School",
              "notes": null
            },
            {
              "word": "Dariss",
              "translation": "Lesson",
              "notes": null
            },
            {
              "word": "kthāwa",
              "translation": "Book",
              "notes": null
            },
            {
              "word": "qalāma",
              "translation": "Pencil",
              "notes": null
            },
            {
              "word": "koorsey",
              "translation": "Chair",
              "notes": null
            },
            {
              "word": "warāqa",
              "translation": "Paper",
              "notes": null
            }
          ]
        }
      ]
    },
	{
      "lesson_number": 2,
      "lesson_title": "To Be (future), To Go (present)",
      "lesson_sections": 2,
      "preliminary_notes": "",
      "lesson_contents": [
        {
          "verbs": [
            {
              "verb": "TO BE",
              "verb_root": "hwa",
              "verb_tense": "FUTURE",
              "conjugations": [
                {
                  "pronoun": "āna",
                  "conjugation": "zee-win",
                  "translation": "I (m) will be"
                },
                {
                  "pronoun": "āna",
                  "conjugation": "zee-wan",
                  "translation": "I (f) will be"
                },
                {
                  "pronoun": "āyit",
                  "conjugation": "zee-wit",
                  "translation": "You (m) will be"
                },
                {
                  "pronoun": "āyat",
                  "conjugation": "zee-wat",
                  "translation": "You (f) will be"
                },
                {
                  "pronoun": "āwo",
                  "conjugation": "zee-lih",
                  "translation": "He will be"
                },
                {
                  "pronoun": "āya/āyee",
                  "conjugation": "zee-lah",
                  "translation": "She will be"
                },
                {
                  "pronoun": "akhny",
                  "conjugation": "zee-wookh",
                  "translation": "We will be"
                },
                {
                  "pronoun": "akhtu(n)",
                  "conjugation": "zee-wotu(n)",
                  "translation": "Y'all will be"
                },
                {
                  "pronoun": "anay/anee",
                  "conjugation": "zee-lay",
                  "translation": "They will be"
                }
              ]
            },
            {
              "verb": "TO GO",
              "verb_root": "izzal",
              "verb_tense": "PRESENT",
              "conjugations": [
                {
                  "pronoun": "āna",
                  "conjugation": "k-zāl-ee",
                  "translation": "I go"
                },
                {
                  "pronoun": "āyit",
                  "conjugation": "k-zāl-ookh",
                  "translation": "You (m) go"
                },
                {
                  "pronoun": "āyat",
                  "conjugation": "k-zāl-akh",
                  "translation": "You (f) go"
                },
                {
                  "pronoun": "āwo",
                  "conjugation": "k-zāl-eh",
                  "translation": "He goes"
                },
                {
                  "pronoun": "āya",
                  "conjugation": "k-zāl-ah",
                  "translation": "She goes"
                },
                {
                  "pronoun": "akhny",
                  "conjugation": "k-zāl-an",
                  "translation": "We go"
                },
                {
                  "pronoun": "akhtu(n)",
                  "conjugation": "k-zāl-otu(n)",
                  "translation": "Y'all go"
                },
                {
                  "pronoun": "anay",
                  "conjugation": "k-zāl-ay",
                  "translation": "They go"
                }
              ]
            }
          ]
        }
      ]
    }
  ]
}
